calamus/__init__.py
calamus/fields.py
calamus/schema.py
calamus/utils.py
calamus-0.4.3.dist-info/LICENSE
calamus-0.4.3.dist-info/METADATA
calamus-0.4.3.dist-info/WHEEL
calamus-0.4.3.dist-info/RECORD
