Metadata-Version: 2.1
Name: calamus
Version: 0.4.3
Summary: calamus is a library built on top of marshmallow to allow (de-)Serialization of Python classes to JSON-LD.
Home-page: https://github.com/SwissDataScienceCenter/calamus/
License: Apache-2.0
Author: Swiss Data Science Center
Author-email: contact@datascience.ch
Requires-Python: >=3.9.1,<4.0.0
Classifier: Development Status :: 4 - Beta
Classifier: Intended Audience :: Developers
Classifier: Intended Audience :: Science/Research
Classifier: License :: OSI Approved :: Apache Software License
Classifier: Operating System :: OS Independent
Classifier: Programming Language :: Python
Classifier: Programming Language :: Python :: 3
Classifier: Programming Language :: Python :: 3.10
Classifier: Programming Language :: Python :: 3.11
Classifier: Programming Language :: Python :: 3.12
Classifier: Programming Language :: Python :: 3.13
Classifier: Programming Language :: Python :: 3.7
Classifier: Programming Language :: Python :: 3.8
Classifier: Programming Language :: Python :: 3.9
Classifier: Topic :: Software Development :: Libraries :: Python Modules
Provides-Extra: docs
Requires-Dist: Jinja2 (>=3.0.0,<3.1.0) ; extra == "docs"
Requires-Dist: lazy-object-proxy (>=1.4.3,<2.0.0)
Requires-Dist: marshmallow (>=3.23.0,<3.24.0)
Requires-Dist: pyld (>=2.0.2,<3.0.0)
Requires-Dist: rdflib (>=6.0.0,<7.0.0)
Requires-Dist: sphinx (>=5.0.0,<6.0.0) ; extra == "docs"
Requires-Dist: sphinx-rtd-theme (>=0.4.3,<0.5.0) ; extra == "docs"
Requires-Dist: sphinxcontrib-spelling (>=5.0.0,<6.0.0) ; extra == "docs"
Project-URL: Repository, https://github.com/SwissDataScienceCenter/calamus/
